ec95/__init__.py
ec95/pr_tasks.json
ec95/search.py
ec95/teor_tasks.json
ec95-1.0.4.dist-info/METADATA
ec95-1.0.4.dist-info/WHEEL
ec95-1.0.4.dist-info/top_level.txt
ec95-1.0.4.dist-info/RECORD
