Metadata-Version: 2.1
Name: ec95
Version: 1.0.4
Summary: xD
Author: qdzzzxc
Keywords: example python
Classifier: Programming Language :: Python :: 3.7
Classifier: License :: OSI Approved :: MIT License
Classifier: Operating System :: OS Independent
Requires-Python: >=3.7
Requires-Dist: pyperclip >=1.8.2
Requires-Dist: joblib >=1.4.2
Requires-Dist: scipy >=1.13.1
Requires-Dist: threadpoolctl >=3.5.0
